{
  "All Models": {
    "1957": [
      {
        "display_name": "Mardi Gras Red",
        "paint_code": "P-913",
        "slug": "mardi-gras-red-p-913",
        "reference_url": "https://www.paintscratch.com/colors/amc/mardi-gras-red-p-913/",
        "source_label": "PaintScratch 1957 AMC",
        "hex_value": "#F31515"
      },
      {
        "display_name": "Carribean Blue",
        "paint_code": "P-905",
        "slug": "carribean-blue-p-905",
        "reference_url": "https://www.paintscratch.com/colors/amc/carribean-blue-p-905/",
        "source_label": "PaintScratch 1957 AMC",
        "hex_value": "#A7E3E2"
      }
    ],
    "1958": [
      {
        "display_name": "Mardi Gras Red",
        "paint_code": "P-913",
        "slug": "mardi-gras-red-p-913",
        "reference_url": "https://www.paintscratch.com/colors/amc/mardi-gras-red-p-913/",
        "source_label": "PaintScratch 1958 AMC",
        "hex_value": "#F31515"
      },
      {
        "display_name": "Light Aqua",
        "paint_code": "P-97",
        "slug": "light-aqua-p-97",
        "reference_url": "https://www.paintscratch.com/colors/amc/light-aqua-p-97/",
        "source_label": "PaintScratch 1958 AMC",
        "hex_value": "#A7E3E2"
      },
      {
        "display_name": "Carribean Blue",
        "paint_code": "P-905",
        "slug": "carribean-blue-p-905",
        "reference_url": "https://www.paintscratch.com/colors/amc/carribean-blue-p-905/",
        "source_label": "PaintScratch 1958 AMC",
        "hex_value": "#A7E3E2"
      }
    ],
    "1959": [
      {
        "display_name": "Mardi Gras Red",
        "paint_code": "P-913",
        "slug": "mardi-gras-red-p-913",
        "reference_url": "https://www.paintscratch.com/colors/amc/mardi-gras-red-p-913/",
        "source_label": "PaintScratch 1959 AMC",
        "hex_value": "#F31515"
      },
      {
        "display_name": "Carribean Blue",
        "paint_code": "P-905",
        "slug": "carribean-blue-p-905",
        "reference_url": "https://www.paintscratch.com/colors/amc/carribean-blue-p-905/",
        "source_label": "PaintScratch 1959 AMC",
        "hex_value": "#A7E3E2"
      }
    ],
    "1960": [
      {
        "display_name": "Mardi Gras Red",
        "paint_code": "P-913",
        "slug": "mardi-gras-red-p-913",
        "reference_url": "https://www.paintscratch.com/colors/amc/mardi-gras-red-p-913/",
        "source_label": "PaintScratch 1960 AMC",
        "hex_value": "#F31515"
      },
      {
        "display_name": "Carribean Blue",
        "paint_code": "P-905",
        "slug": "carribean-blue-p-905",
        "reference_url": "https://www.paintscratch.com/colors/amc/carribean-blue-p-905/",
        "source_label": "PaintScratch 1960 AMC",
        "hex_value": "#A7E3E2"
      },
      {
        "display_name": "Placid Blue",
        "paint_code": "P10",
        "slug": "placid-blue-p10",
        "reference_url": "https://www.paintscratch.com/colors/amc/placid-blue-p10/",
        "source_label": "PaintScratch 1960 AMC",
        "hex_value": "#DBFDFD"
      }
    ],
    "1961": [
      {
        "display_name": "Mardi Gras Red",
        "paint_code": "P-913",
        "slug": "mardi-gras-red-p-913",
        "reference_url": "https://www.paintscratch.com/colors/amc/mardi-gras-red-p-913/",
        "source_label": "PaintScratch 1961 AMC",
        "hex_value": "#F31515"
      },
      {
        "display_name": "Classic Black",
        "paint_code": "P-1",
        "slug": "classic-black-p-1",
        "reference_url": "https://www.paintscratch.com/colors/amc/classic-black-p-1/",
        "source_label": "PaintScratch 1961 AMC",
        "hex_value": "#000000"
      },
      {
        "display_name": "Carribean Blue",
        "paint_code": "P-905",
        "slug": "carribean-blue-p-905",
        "reference_url": "https://www.paintscratch.com/colors/amc/carribean-blue-p-905/",
        "source_label": "PaintScratch 1961 AMC",
        "hex_value": "#A7E3E2"
      }
    ],
    "1962": [
      {
        "display_name": "Frost White",
        "paint_code": "P-72",
        "slug": "frost-white-p-72",
        "reference_url": "https://www.paintscratch.com/colors/amc/frost-white-p-72/",
        "source_label": "PaintScratch 1962 AMC",
        "hex_value": "#FEFEFC"
      },
      {
        "display_name": "Classic Black",
        "paint_code": "P-1",
        "slug": "classic-black-p-1",
        "reference_url": "https://www.paintscratch.com/colors/amc/classic-black-p-1/",
        "source_label": "PaintScratch 1962 AMC",
        "hex_value": "#000000"
      },
      {
        "display_name": "Aqua Mist Poly",
        "paint_code": "P-15",
        "slug": "aqua-mist-poly-p-15",
        "reference_url": "https://www.paintscratch.com/colors/amc/aqua-mist-poly-p-15/",
        "source_label": "PaintScratch 1962 AMC",
        "hex_value": "#537B7B"
      },
      {
        "display_name": "Sonata Blue",
        "paint_code": "P-27",
        "slug": "sonata-blue-p-27",
        "reference_url": "https://www.paintscratch.com/colors/amc/sonata-blue-p-27/",
        "source_label": "PaintScratch 1962 AMC",
        "hex_value": "#B8C6CE"
      },
      {
        "display_name": "Briarcliff Red",
        "paint_code": "P-30",
        "slug": "briarcliff-red-p-30",
        "reference_url": "https://www.paintscratch.com/colors/amc/briarcliff-red-p-30/",
        "source_label": "PaintScratch 1962 AMC",
        "hex_value": "#8A282A"
      },
      {
        "display_name": "Inca Silver Poly",
        "paint_code": "P-31",
        "slug": "inca-silver-poly-p-31",
        "reference_url": "https://www.paintscratch.com/colors/amc/inca-silver-poly-p-31/",
        "source_label": "PaintScratch 1962 AMC",
        "hex_value": "#CDD0D5"
      },
      {
        "display_name": "Jasmine Rose",
        "paint_code": "P-33",
        "slug": "jasmine-rose-p-33",
        "reference_url": "https://www.paintscratch.com/colors/amc/jasmine-rose-p-33/",
        "source_label": "PaintScratch 1962 AMC",
        "hex_value": "#8D3D56"
      },
      {
        "display_name": "Baron Blue Poly",
        "paint_code": "P-35",
        "slug": "baron-blue-poly-p-35",
        "reference_url": "https://www.paintscratch.com/colors/amc/baron-blue-poly-p-35/",
        "source_label": "PaintScratch 1962 AMC",
        "hex_value": "#446986"
      },
      {
        "display_name": "Glen Cove Green",
        "paint_code": "P-36",
        "slug": "glen-cove-green-p-36",
        "reference_url": "https://www.paintscratch.com/colors/amc/glen-cove-green-p-36/",
        "source_label": "PaintScratch 1962 AMC",
        "hex_value": "#8ABBB6"
      },
      {
        "display_name": "Elmhurst Green Poly",
        "paint_code": "P-37",
        "slug": "elmhurst-green-poly-p-37",
        "reference_url": "https://www.paintscratch.com/colors/amc/elmhurst-green-poly-p-37/",
        "source_label": "PaintScratch 1962 AMC",
        "hex_value": "#324C3E"
      },
      {
        "display_name": "Algiers Rose Copper Poly",
        "paint_code": "P-38",
        "slug": "algiers-rose-copper-poly-p-38",
        "reference_url": "https://www.paintscratch.com/colors/amc/algiers-rose-copper-poly-p-38/",
        "source_label": "PaintScratch 1962 AMC",
        "hex_value": "#7A422A"
      },
      {
        "display_name": "Red Poly",
        "paint_code": "P-39",
        "slug": "red-poly-p-39",
        "reference_url": "https://www.paintscratch.com/colors/amc/red-poly-p-39/",
        "source_label": "PaintScratch 1962 AMC",
        "hex_value": "#743F3E"
      },
      {
        "display_name": "Majestic Blue Poly",
        "paint_code": "P-40",
        "slug": "majestic-blue-poly-p-40",
        "reference_url": "https://www.paintscratch.com/colors/amc/majestic-blue-poly-p-40/",
        "source_label": "PaintScratch 1962 AMC",
        "hex_value": "#617BA3"
      },
      {
        "display_name": "Corsican Gold Poly",
        "paint_code": "P-41",
        "slug": "corsican-gold-poly-p-41",
        "reference_url": "https://www.paintscratch.com/colors/amc/corsican-gold-poly-p-41/",
        "source_label": "PaintScratch 1962 AMC",
        "hex_value": "#AD9131"
      },
      {
        "display_name": "Festival Rose",
        "paint_code": "P25",
        "slug": "festival-rose-p25",
        "reference_url": "https://www.paintscratch.com/colors/amc/festival-rose-p25/",
        "source_label": "PaintScratch 1962 AMC",
        "hex_value": "#EC8C8C"
      }
    ],
    "1963": [
      {
        "display_name": "Classic Black",
        "paint_code": "P-1",
        "slug": "classic-black-p-1",
        "reference_url": "https://www.paintscratch.com/colors/amc/classic-black-p-1/",
        "source_label": "PaintScratch 1963 AMC",
        "hex_value": "#000000"
      },
      {
        "display_name": "Briarcliff Red",
        "paint_code": "P-30",
        "slug": "briarcliff-red-p-30",
        "reference_url": "https://www.paintscratch.com/colors/amc/briarcliff-red-p-30/",
        "source_label": "PaintScratch 1963 AMC",
        "hex_value": "#8A282A"
      }
    ],
    "1964": [
      {
        "display_name": "Classic Black",
        "paint_code": "P-1",
        "slug": "classic-black-p-1",
        "reference_url": "https://www.paintscratch.com/colors/amc/classic-black-p-1/",
        "source_label": "PaintScratch 1964 AMC",
        "hex_value": "#000000"
      },
      {
        "display_name": "Light Aqua",
        "paint_code": "P-56",
        "slug": "light-aqua-p-56",
        "reference_url": "https://www.paintscratch.com/colors/amc/light-aqua-p-56/",
        "source_label": "PaintScratch 1964 AMC",
        "hex_value": "#A7E3E2"
      }
    ],
    "1965": [
      {
        "display_name": "Classic Black",
        "paint_code": "P-1",
        "slug": "classic-black-p-1",
        "reference_url": "https://www.paintscratch.com/colors/amc/classic-black-p-1/",
        "source_label": "PaintScratch 1965 AMC",
        "hex_value": "#000000"
      },
      {
        "display_name": "White Metallic",
        "paint_code": "P72A",
        "slug": "white-metallic-p72a",
        "reference_url": "https://www.paintscratch.com/colors/amc/white-metallic-p72a/",
        "source_label": "PaintScratch 1965 AMC",
        "hex_value": "#F6F6F0"
      }
    ],
    "1967": [
      {
        "display_name": "Matador Red",
        "paint_code": "39A",
        "slug": "matador-red-39a",
        "reference_url": "https://www.paintscratch.com/colors/amc/matador-red-39a/",
        "source_label": "PaintScratch 1967 AMC",
        "hex_value": "#A32A1D"
      },
      {
        "display_name": "Yuma Tan Metallic",
        "paint_code": "36A",
        "slug": "yuma-tan-metallic-36a",
        "reference_url": "https://www.paintscratch.com/colors/amc/yuma-tan-metallic-36a/",
        "source_label": "PaintScratch 1967 AMC",
        "hex_value": "#D1A341"
      },
      {
        "display_name": "Barbados Blue Poly",
        "paint_code": "P-32A",
        "slug": "barbados-blue-poly-p-32a",
        "reference_url": "https://www.paintscratch.com/colors/amc/barbados-blue-poly-p-32a/",
        "source_label": "PaintScratch 1967 AMC",
        "hex_value": "#495EA3"
      },
      {
        "display_name": "Amber Sungold Poly",
        "paint_code": "P-37A",
        "slug": "amber-sungold-poly-p-37a",
        "reference_url": "https://www.paintscratch.com/colors/amc/amber-sungold-poly-p-37a/",
        "source_label": "PaintScratch 1967 AMC",
        "hex_value": "#E3BD25"
      },
      {
        "display_name": "Med Aqua",
        "paint_code": "P8-A",
        "slug": "med-aqua-p8-a",
        "reference_url": "https://www.paintscratch.com/colors/amc/med-aqua-p8-a/",
        "source_label": "PaintScratch 1967 AMC",
        "hex_value": "#468D8E"
      }
    ],
    "1968": [
      {
        "display_name": "Rally Green Metallic",
        "paint_code": "47A",
        "slug": "rally-green-metallic-47a",
        "reference_url": "https://www.paintscratch.com/colors/amc/rally-green-metallic-47a/",
        "source_label": "PaintScratch 1968 AMC",
        "hex_value": "#576F51"
      },
      {
        "display_name": "Laurel Green Metallic",
        "paint_code": "P46A",
        "slug": "laurel-green-metallic-p46a",
        "reference_url": "https://www.paintscratch.com/colors/amc/laurel-green-metallic-p46a/",
        "source_label": "PaintScratch 1968 AMC",
        "hex_value": "#9CB860"
      },
      {
        "display_name": "Hialeah Yellow",
        "paint_code": "P58A",
        "slug": "hialeah-yellow-p58a",
        "reference_url": "https://www.paintscratch.com/colors/amc/hialeah-yellow-p58a/",
        "source_label": "PaintScratch 1968 AMC",
        "hex_value": "#FFFF00"
      }
    ],
    "1969": [
      {
        "display_name": "Frost White",
        "paint_code": "P-72",
        "slug": "frost-white-p-72",
        "reference_url": "https://www.paintscratch.com/colors/amc/frost-white-p-72/",
        "source_label": "PaintScratch 1969 AMC",
        "hex_value": "#FEFEFC"
      },
      {
        "display_name": "Hunter Green",
        "paint_code": "P71",
        "slug": "hunter-green-p71",
        "reference_url": "https://www.paintscratch.com/colors/amc/hunter-green-p71/",
        "source_label": "PaintScratch 1969 AMC",
        "hex_value": "#15350F"
      },
      {
        "display_name": "Rally Green Metallic",
        "paint_code": "47A",
        "slug": "rally-green-metallic-47a",
        "reference_url": "https://www.paintscratch.com/colors/amc/rally-green-metallic-47a/",
        "source_label": "PaintScratch 1969 AMC",
        "hex_value": "#576F51"
      },
      {
        "display_name": "Willow Green",
        "paint_code": "P75",
        "slug": "willow-green-p75",
        "reference_url": "https://www.paintscratch.com/colors/amc/willow-green-p75/",
        "source_label": "PaintScratch 1969 AMC",
        "hex_value": "#9C8C08"
      },
      {
        "display_name": "Bronze",
        "paint_code": "P79",
        "slug": "bronze-p79",
        "reference_url": "https://www.paintscratch.com/colors/amc/bronze-p79/",
        "source_label": "PaintScratch 1969 AMC",
        "hex_value": "#C57E3F"
      }
    ],
    "1970": [
      {
        "display_name": "Big Bad Orange",
        "paint_code": "P-3",
        "slug": "big-bad-orange-p-3",
        "reference_url": "https://www.paintscratch.com/colors/amc/big-bad-orange-p-3/",
        "source_label": "PaintScratch 1970 AMC",
        "hex_value": "#DD6023"
      },
      {
        "display_name": "Frost White",
        "paint_code": "P-72",
        "slug": "frost-white-p-72",
        "reference_url": "https://www.paintscratch.com/colors/amc/frost-white-p-72/",
        "source_label": "PaintScratch 1970 AMC",
        "hex_value": "#FEFEFC"
      },
      {
        "display_name": "Bittersweet Orange Poly",
        "paint_code": "P-79",
        "slug": "bittersweet-orange-poly-p-79",
        "reference_url": "https://www.paintscratch.com/colors/amc/bittersweet-orange-poly-p-79/",
        "source_label": "PaintScratch 1970 AMC",
        "hex_value": "#AD8135"
      },
      {
        "display_name": "Electric Blue Poly",
        "paint_code": "B-6",
        "slug": "electric-blue-poly-b-6",
        "reference_url": "https://www.paintscratch.com/colors/amc/electric-blue-poly-b-6/",
        "source_label": "PaintScratch 1970 AMC",
        "hex_value": "#2978D1"
      },
      {
        "display_name": "Classic Black",
        "paint_code": "P-1",
        "slug": "classic-black-p-1",
        "reference_url": "https://www.paintscratch.com/colors/amc/classic-black-p-1/",
        "source_label": "PaintScratch 1970 AMC",
        "hex_value": "#000000"
      },
      {
        "display_name": "Big Bad Blue",
        "paint_code": "P-2",
        "slug": "big-bad-blue-p-2",
        "reference_url": "https://www.paintscratch.com/colors/amc/big-bad-blue-p-2/",
        "source_label": "PaintScratch 1970 AMC",
        "hex_value": "#2B5D95"
      },
      {
        "display_name": "Big Bad Green",
        "paint_code": "P-4",
        "slug": "big-bad-green-p-4",
        "reference_url": "https://www.paintscratch.com/colors/amc/big-bad-green-p-4/",
        "source_label": "PaintScratch 1970 AMC",
        "hex_value": "#40A638"
      },
      {
        "display_name": "Shadow Black",
        "paint_code": "P-8",
        "slug": "shadow-black-p-8",
        "reference_url": "https://www.paintscratch.com/colors/amc/shadow-black-p-8/",
        "source_label": "PaintScratch 1970 AMC",
        "hex_value": "#0A0A0A"
      },
      {
        "display_name": "Red Poly",
        "paint_code": "P-39",
        "slug": "red-poly-p-39",
        "reference_url": "https://www.paintscratch.com/colors/amc/red-poly-p-39/",
        "source_label": "PaintScratch 1970 AMC",
        "hex_value": "#743F3E"
      },
      {
        "display_name": "Mialeah Yellow",
        "paint_code": "P-58",
        "slug": "mialeah-yellow-p-58",
        "reference_url": "https://www.paintscratch.com/colors/amc/mialeah-yellow-p-58/",
        "source_label": "PaintScratch 1970 AMC",
        "hex_value": "#CDBA19"
      },
      {
        "display_name": "Villa Red Poly",
        "paint_code": "P-80",
        "slug": "villa-red-poly-p-80",
        "reference_url": "https://www.paintscratch.com/colors/amc/villa-red-poly-p-80/",
        "source_label": "PaintScratch 1970 AMC",
        "hex_value": "#743F3E"
      },
      {
        "display_name": "Gray",
        "paint_code": "P-81",
        "slug": "gray-p-81",
        "reference_url": "https://www.paintscratch.com/colors/amc/gray-p-81/",
        "source_label": "PaintScratch 1970 AMC",
        "hex_value": "#828890"
      },
      {
        "display_name": "Bayshore Blue Poly",
        "paint_code": "P-82",
        "slug": "bayshore-blue-poly-p-82",
        "reference_url": "https://www.paintscratch.com/colors/amc/bayshore-blue-poly-p-82/",
        "source_label": "PaintScratch 1970 AMC",
        "hex_value": "#96B7CA"
      },
      {
        "display_name": "Commodore Blue Poly",
        "paint_code": "P-84",
        "slug": "commodore-blue-poly-p-84",
        "reference_url": "https://www.paintscratch.com/colors/amc/commodore-blue-poly-p-84/",
        "source_label": "PaintScratch 1970 AMC",
        "hex_value": "#304F60"
      },
      {
        "display_name": "Sea Foam Aqua Ply",
        "paint_code": "P-85",
        "slug": "sea-foam-aqua-ply-p-85",
        "reference_url": "https://www.paintscratch.com/colors/amc/sea-foam-aqua-ply-p-85/",
        "source_label": "PaintScratch 1970 AMC",
        "hex_value": "#769C9B"
      },
      {
        "display_name": "Mosport Green Poly",
        "paint_code": "P-86",
        "slug": "mosport-green-poly-p-86",
        "reference_url": "https://www.paintscratch.com/colors/amc/mosport-green-poly-p-86/",
        "source_label": "PaintScratch 1970 AMC",
        "hex_value": "#337B64"
      }
    ],
    "1971": [
      {
        "display_name": "Big Bad Orange",
        "paint_code": "P-3",
        "slug": "big-bad-orange-p-3",
        "reference_url": "https://www.paintscratch.com/colors/amc/big-bad-orange-p-3/",
        "source_label": "PaintScratch 1971 AMC",
        "hex_value": "#DD6023"
      },
      {
        "display_name": "Frost White",
        "paint_code": "P-72",
        "slug": "frost-white-p-72",
        "reference_url": "https://www.paintscratch.com/colors/amc/frost-white-p-72/",
        "source_label": "PaintScratch 1971 AMC",
        "hex_value": "#FEFEFC"
      },
      {
        "display_name": "Bittersweet Orange Poly",
        "paint_code": "P-79",
        "slug": "bittersweet-orange-poly-p-79",
        "reference_url": "https://www.paintscratch.com/colors/amc/bittersweet-orange-poly-p-79/",
        "source_label": "PaintScratch 1971 AMC",
        "hex_value": "#AD8135"
      },
      {
        "display_name": "Electric Blue Poly",
        "paint_code": "B-6",
        "slug": "electric-blue-poly-b-6",
        "reference_url": "https://www.paintscratch.com/colors/amc/electric-blue-poly-b-6/",
        "source_label": "PaintScratch 1971 AMC",
        "hex_value": "#2978D1"
      },
      {
        "display_name": "Mustard Yellow",
        "paint_code": "B8",
        "slug": "mustard-yellow-b8",
        "reference_url": "https://www.paintscratch.com/colors/amc/mustard-yellow-b8/",
        "source_label": "PaintScratch 1971 AMC",
        "hex_value": "#FFDE01"
      },
      {
        "display_name": "Classic Black",
        "paint_code": "P-1",
        "slug": "classic-black-p-1",
        "reference_url": "https://www.paintscratch.com/colors/amc/classic-black-p-1/",
        "source_label": "PaintScratch 1971 AMC",
        "hex_value": "#000000"
      },
      {
        "display_name": "Big Bad Blue",
        "paint_code": "P-2",
        "slug": "big-bad-blue-p-2",
        "reference_url": "https://www.paintscratch.com/colors/amc/big-bad-blue-p-2/",
        "source_label": "PaintScratch 1971 AMC",
        "hex_value": "#2B5D95"
      },
      {
        "display_name": "Big Bad Green",
        "paint_code": "P-4",
        "slug": "big-bad-green-p-4",
        "reference_url": "https://www.paintscratch.com/colors/amc/big-bad-green-p-4/",
        "source_label": "PaintScratch 1971 AMC",
        "hex_value": "#40A638"
      },
      {
        "display_name": "Shadow Black",
        "paint_code": "P-8",
        "slug": "shadow-black-p-8",
        "reference_url": "https://www.paintscratch.com/colors/amc/shadow-black-p-8/",
        "source_label": "PaintScratch 1971 AMC",
        "hex_value": "#0A0A0A"
      },
      {
        "display_name": "Red Poly",
        "paint_code": "P-39",
        "slug": "red-poly-p-39",
        "reference_url": "https://www.paintscratch.com/colors/amc/red-poly-p-39/",
        "source_label": "PaintScratch 1971 AMC",
        "hex_value": "#743F3E"
      },
      {
        "display_name": "Mialeah Yellow",
        "paint_code": "P-58",
        "slug": "mialeah-yellow-p-58",
        "reference_url": "https://www.paintscratch.com/colors/amc/mialeah-yellow-p-58/",
        "source_label": "PaintScratch 1971 AMC",
        "hex_value": "#CDBA19"
      },
      {
        "display_name": "Villa Red Poly",
        "paint_code": "P-80",
        "slug": "villa-red-poly-p-80",
        "reference_url": "https://www.paintscratch.com/colors/amc/villa-red-poly-p-80/",
        "source_label": "PaintScratch 1971 AMC",
        "hex_value": "#743F3E"
      },
      {
        "display_name": "Gray",
        "paint_code": "P-81",
        "slug": "gray-p-81",
        "reference_url": "https://www.paintscratch.com/colors/amc/gray-p-81/",
        "source_label": "PaintScratch 1971 AMC",
        "hex_value": "#828890"
      },
      {
        "display_name": "Bayshore Blue Poly",
        "paint_code": "P-82",
        "slug": "bayshore-blue-poly-p-82",
        "reference_url": "https://www.paintscratch.com/colors/amc/bayshore-blue-poly-p-82/",
        "source_label": "PaintScratch 1971 AMC",
        "hex_value": "#96B7CA"
      },
      {
        "display_name": "Commodore Blue Poly",
        "paint_code": "P-84",
        "slug": "commodore-blue-poly-p-84",
        "reference_url": "https://www.paintscratch.com/colors/amc/commodore-blue-poly-p-84/",
        "source_label": "PaintScratch 1971 AMC",
        "hex_value": "#304F60"
      },
      {
        "display_name": "Sea Foam Aqua Ply",
        "paint_code": "P-85",
        "slug": "sea-foam-aqua-ply-p-85",
        "reference_url": "https://www.paintscratch.com/colors/amc/sea-foam-aqua-ply-p-85/",
        "source_label": "PaintScratch 1971 AMC",
        "hex_value": "#769C9B"
      }
    ],
    "1972": [
      {
        "display_name": "Snow White",
        "paint_code": "A1",
        "slug": "snow-white-a1",
        "reference_url": "https://www.paintscratch.com/colors/amc/snow-white-a1/",
        "source_label": "PaintScratch 1972 AMC",
        "hex_value": "#F6F6F0"
      },
      {
        "display_name": "Surfside Turquoise",
        "paint_code": "C6",
        "slug": "surfside-turquoise-c6",
        "reference_url": "https://www.paintscratch.com/colors/amc/surfside-turquoise-c6/",
        "source_label": "PaintScratch 1972 AMC",
        "hex_value": "#A7E3E2"
      },
      {
        "display_name": "Grasshoppper Green Metallic",
        "paint_code": "C8",
        "slug": "grasshoppper-green-metallic-c8",
        "reference_url": "https://www.paintscratch.com/colors/amc/grasshoppper-green-metallic-c8/",
        "source_label": "PaintScratch 1972 AMC",
        "hex_value": "#2B4D37"
      },
      {
        "display_name": "Bright Green",
        "paint_code": "D1",
        "slug": "bright-green-d1",
        "reference_url": "https://www.paintscratch.com/colors/amc/bright-green-d1/",
        "source_label": "PaintScratch 1972 AMC",
        "hex_value": "#37B515"
      },
      {
        "display_name": "Orange",
        "paint_code": "D5",
        "slug": "orange-d5",
        "reference_url": "https://www.paintscratch.com/colors/amc/orange-d5/",
        "source_label": "PaintScratch 1972 AMC",
        "hex_value": "#EB9D23"
      },
      {
        "display_name": "Bright Red",
        "paint_code": "D7",
        "slug": "bright-red-d7",
        "reference_url": "https://www.paintscratch.com/colors/amc/bright-red-d7/",
        "source_label": "PaintScratch 1972 AMC",
        "hex_value": "#F31515"
      },
      {
        "display_name": "Sparkling Burgandy",
        "paint_code": "D8",
        "slug": "sparkling-burgandy-d8",
        "reference_url": "https://www.paintscratch.com/colors/amc/sparkling-burgandy-d8/",
        "source_label": "PaintScratch 1972 AMC",
        "hex_value": "#761C1A"
      },
      {
        "display_name": "Wild Plum",
        "paint_code": "D9",
        "slug": "wild-plum-d9",
        "reference_url": "https://www.paintscratch.com/colors/amc/wild-plum-d9/",
        "source_label": "PaintScratch 1972 AMC",
        "hex_value": "#310D1A"
      }
    ],
    "1973": [
      {
        "display_name": "Fresh Plum Metallic",
        "paint_code": "F3",
        "slug": "fresh-plum-metallic-f3",
        "reference_url": "https://www.paintscratch.com/colors/amc/fresh-plum-metallic-f3/",
        "source_label": "PaintScratch 1973 AMC",
        "hex_value": "#661240"
      },
      {
        "display_name": "Olympic Blue Metallic",
        "paint_code": "E2",
        "slug": "olympic-blue-metallic-e2",
        "reference_url": "https://www.paintscratch.com/colors/amc/olympic-blue-metallic-e2/",
        "source_label": "PaintScratch 1973 AMC",
        "hex_value": "#4B5C93"
      }
    ],
    "1974": [
      {
        "display_name": "Silver Green Metalic",
        "paint_code": "G-1",
        "slug": "silver-green-metalic-g-1",
        "reference_url": "https://www.paintscratch.com/colors/amc/silver-green-metalic-g-1/",
        "source_label": "PaintScratch 1974 AMC",
        "hex_value": "#FFFFFF"
      },
      {
        "display_name": "Snow White",
        "paint_code": "A1",
        "slug": "snow-white-a1",
        "reference_url": "https://www.paintscratch.com/colors/amc/snow-white-a1/",
        "source_label": "PaintScratch 1974 AMC",
        "hex_value": "#F6F6F0"
      },
      {
        "display_name": "Bright Red",
        "paint_code": "D7",
        "slug": "bright-red-d7",
        "reference_url": "https://www.paintscratch.com/colors/amc/bright-red-d7/",
        "source_label": "PaintScratch 1974 AMC",
        "hex_value": "#F31515"
      },
      {
        "display_name": "Copper Metallic (Dupont 42850)",
        "paint_code": "F-9",
        "slug": "copper-metallic-dupont-42850-f-9",
        "reference_url": "https://www.paintscratch.com/colors/amc/copper-metallic-dupont-42850-f-9/",
        "source_label": "PaintScratch 1974 AMC",
        "hex_value": "#5F3026"
      },
      {
        "display_name": "Medium Blue",
        "paint_code": "F2",
        "slug": "medium-blue-f2",
        "reference_url": "https://www.paintscratch.com/colors/amc/medium-blue-f2/",
        "source_label": "PaintScratch 1974 AMC",
        "hex_value": "#0D2D97"
      },
      {
        "display_name": "Copper",
        "paint_code": "F9",
        "slug": "copper-f9",
        "reference_url": "https://www.paintscratch.com/colors/amc/copper-f9/",
        "source_label": "PaintScratch 1974 AMC",
        "hex_value": "#985636"
      },
      {
        "display_name": "Medium Purple",
        "paint_code": "G-4",
        "slug": "medium-purple-g-4",
        "reference_url": "https://www.paintscratch.com/colors/amc/medium-purple-g-4/",
        "source_label": "PaintScratch 1974 AMC",
        "hex_value": "#DC3272"
      },
      {
        "display_name": "Sienna Orange",
        "paint_code": "G6",
        "slug": "sienna-orange-g6",
        "reference_url": "https://www.paintscratch.com/colors/amc/sienna-orange-g6/",
        "source_label": "PaintScratch 1974 AMC",
        "hex_value": "#EB9D23"
      },
      {
        "display_name": "Tan",
        "paint_code": "J-8",
        "slug": "tan-j-8",
        "reference_url": "https://www.paintscratch.com/colors/amc/tan-j-8/",
        "source_label": "PaintScratch 1974 AMC",
        "hex_value": "#D1A341"
      }
    ],
    "1975": [
      {
        "display_name": "Copper Metallic (Dupont 42850)",
        "paint_code": "F-9",
        "slug": "copper-metallic-dupont-42850-f-9",
        "reference_url": "https://www.paintscratch.com/colors/amc/copper-metallic-dupont-42850-f-9/",
        "source_label": "PaintScratch 1975 AMC",
        "hex_value": "#5F3026"
      },
      {
        "display_name": "Copper",
        "paint_code": "F9",
        "slug": "copper-f9",
        "reference_url": "https://www.paintscratch.com/colors/amc/copper-f9/",
        "source_label": "PaintScratch 1975 AMC",
        "hex_value": "#985636"
      },
      {
        "display_name": "Tan",
        "paint_code": "J-8",
        "slug": "tan-j-8",
        "reference_url": "https://www.paintscratch.com/colors/amc/tan-j-8/",
        "source_label": "PaintScratch 1975 AMC",
        "hex_value": "#D1A341"
      }
    ],
    "1976": [
      {
        "display_name": "Sand Tan",
        "paint_code": "6D",
        "slug": "sand-tan-6d",
        "reference_url": "https://www.paintscratch.com/colors/amc/sand-tan-6d/",
        "source_label": "PaintScratch 1976 AMC",
        "hex_value": "#C8B380"
      },
      {
        "display_name": "Marine Aqua Metallic",
        "paint_code": "6A",
        "slug": "marine-aqua-metallic-6a",
        "reference_url": "https://www.paintscratch.com/colors/amc/marine-aqua-metallic-6a/",
        "source_label": "PaintScratch 1976 AMC",
        "hex_value": "#4F938F"
      },
      {
        "display_name": "Seaspray Green",
        "paint_code": "6B",
        "slug": "seaspray-green-6b",
        "reference_url": "https://www.paintscratch.com/colors/amc/seaspray-green-6b/",
        "source_label": "PaintScratch 1976 AMC",
        "hex_value": "#72BE90"
      },
      {
        "display_name": "Evergreen Metallic",
        "paint_code": "6C",
        "slug": "evergreen-metallic-6c",
        "reference_url": "https://www.paintscratch.com/colors/amc/evergreen-metallic-6c/",
        "source_label": "PaintScratch 1976 AMC",
        "hex_value": "#215D39"
      },
      {
        "display_name": "Burnished Bronze Metallic",
        "paint_code": "6E",
        "slug": "burnished-bronze-metallic-6e",
        "reference_url": "https://www.paintscratch.com/colors/amc/burnished-bronze-metallic-6e/",
        "source_label": "PaintScratch 1976 AMC",
        "hex_value": "#D19F63"
      },
      {
        "display_name": "Silver Frost Metallic",
        "paint_code": "6J",
        "slug": "silver-frost-metallic-6j",
        "reference_url": "https://www.paintscratch.com/colors/amc/silver-frost-metallic-6j/",
        "source_label": "PaintScratch 1976 AMC",
        "hex_value": "#A6A6A6"
      },
      {
        "display_name": "Limefire Metallic",
        "paint_code": "6K",
        "slug": "limefire-metallic-6k",
        "reference_url": "https://www.paintscratch.com/colors/amc/limefire-metallic-6k/",
        "source_label": "PaintScratch 1976 AMC",
        "hex_value": "#70CE79"
      },
      {
        "display_name": "Firecracker Red",
        "paint_code": "6P",
        "slug": "firecracker-red-6p",
        "reference_url": "https://www.paintscratch.com/colors/amc/firecracker-red-6p/",
        "source_label": "PaintScratch 1976 AMC",
        "hex_value": "#D61616"
      },
      {
        "display_name": "Brilliant Blue",
        "paint_code": "6R",
        "slug": "brilliant-blue-6r",
        "reference_url": "https://www.paintscratch.com/colors/amc/brilliant-blue-6r/",
        "source_label": "PaintScratch 1976 AMC",
        "hex_value": "#396DB3"
      },
      {
        "display_name": "Nautical Blue Metallic",
        "paint_code": "6T",
        "slug": "nautical-blue-metallic-6t",
        "reference_url": "https://www.paintscratch.com/colors/amc/nautical-blue-metallic-6t/",
        "source_label": "PaintScratch 1976 AMC",
        "hex_value": "#41738D"
      },
      {
        "display_name": "Sunshine Yellow",
        "paint_code": "6V",
        "slug": "sunshine-yellow-6v",
        "reference_url": "https://www.paintscratch.com/colors/amc/sunshine-yellow-6v/",
        "source_label": "PaintScratch 1976 AMC",
        "hex_value": "#F0DD3A"
      },
      {
        "display_name": "Alpine White",
        "paint_code": "G7",
        "slug": "alpine-white-g7",
        "reference_url": "https://www.paintscratch.com/colors/amc/alpine-white-g7/",
        "source_label": "PaintScratch 1976 AMC",
        "hex_value": "#F9F8E9"
      },
      {
        "display_name": "Medium Blue Metallic",
        "paint_code": "G9",
        "slug": "medium-blue-metallic-g9",
        "reference_url": "https://www.paintscratch.com/colors/amc/medium-blue-metallic-g9/",
        "source_label": "PaintScratch 1976 AMC",
        "hex_value": "#7698AA"
      },
      {
        "display_name": "Dark Cocoa Metallic",
        "paint_code": "H4",
        "slug": "dark-cocoa-metallic-h4",
        "reference_url": "https://www.paintscratch.com/colors/amc/dark-cocoa-metallic-h4/",
        "source_label": "PaintScratch 1976 AMC",
        "hex_value": "#6E3418"
      },
      {
        "display_name": "Golden Jade Metallic",
        "paint_code": "H6",
        "slug": "golden-jade-metallic-h6",
        "reference_url": "https://www.paintscratch.com/colors/amc/golden-jade-metallic-h6/",
        "source_label": "PaintScratch 1976 AMC",
        "hex_value": "#AAA82A"
      },
      {
        "display_name": "Aztec Copper Metallic",
        "paint_code": "H7",
        "slug": "aztec-copper-metallic-h7",
        "reference_url": "https://www.paintscratch.com/colors/amc/aztec-copper-metallic-h7/",
        "source_label": "PaintScratch 1976 AMC",
        "hex_value": "#DA8B56"
      }
    ],
    "1977": [
      {
        "display_name": "Sand Tan",
        "paint_code": "6D",
        "slug": "sand-tan-6d",
        "reference_url": "https://www.paintscratch.com/colors/amc/sand-tan-6d/",
        "source_label": "PaintScratch 1977 AMC",
        "hex_value": "#C8B380"
      },
      {
        "display_name": "Loden Green Metallic",
        "paint_code": "7L",
        "slug": "loden-green-metallic-7l",
        "reference_url": "https://www.paintscratch.com/colors/amc/loden-green-metallic-7l/",
        "source_label": "PaintScratch 1977 AMC",
        "hex_value": "#38612B"
      },
      {
        "display_name": "Golden Ginger Metallic",
        "paint_code": "7M",
        "slug": "golden-ginger-metallic-7m",
        "reference_url": "https://www.paintscratch.com/colors/amc/golden-ginger-metallic-7m/",
        "source_label": "PaintScratch 1977 AMC",
        "hex_value": "#A37349"
      },
      {
        "display_name": "Silver Frost Metallic",
        "paint_code": "6J",
        "slug": "silver-frost-metallic-6j",
        "reference_url": "https://www.paintscratch.com/colors/amc/silver-frost-metallic-6j/",
        "source_label": "PaintScratch 1977 AMC",
        "hex_value": "#A6A6A6"
      },
      {
        "display_name": "Firecracker Red",
        "paint_code": "6P",
        "slug": "firecracker-red-6p",
        "reference_url": "https://www.paintscratch.com/colors/amc/firecracker-red-6p/",
        "source_label": "PaintScratch 1977 AMC",
        "hex_value": "#D61616"
      },
      {
        "display_name": "Brilliant Blue",
        "paint_code": "6R",
        "slug": "brilliant-blue-6r",
        "reference_url": "https://www.paintscratch.com/colors/amc/brilliant-blue-6r/",
        "source_label": "PaintScratch 1977 AMC",
        "hex_value": "#396DB3"
      },
      {
        "display_name": "Sunshine Yellow",
        "paint_code": "6V",
        "slug": "sunshine-yellow-6v",
        "reference_url": "https://www.paintscratch.com/colors/amc/sunshine-yellow-6v/",
        "source_label": "PaintScratch 1977 AMC",
        "hex_value": "#F0DD3A"
      },
      {
        "display_name": "Mocha Brown Metallic",
        "paint_code": "7B",
        "slug": "mocha-brown-metallic-7b",
        "reference_url": "https://www.paintscratch.com/colors/amc/mocha-brown-metallic-7b/",
        "source_label": "PaintScratch 1977 AMC",
        "hex_value": "#654419"
      },
      {
        "display_name": "Autumn Red Metallic",
        "paint_code": "7C",
        "slug": "autumn-red-metallic-7c",
        "reference_url": "https://www.paintscratch.com/colors/amc/autumn-red-metallic-7c/",
        "source_label": "PaintScratch 1977 AMC",
        "hex_value": "#A50D14"
      },
      {
        "display_name": "Powder Blue",
        "paint_code": "7D",
        "slug": "powder-blue-7d",
        "reference_url": "https://www.paintscratch.com/colors/amc/powder-blue-7d/",
        "source_label": "PaintScratch 1977 AMC",
        "hex_value": "#9BBFBF"
      },
      {
        "display_name": "Midnight Blue Metallic",
        "paint_code": "7K",
        "slug": "midnight-blue-metallic-7k",
        "reference_url": "https://www.paintscratch.com/colors/amc/midnight-blue-metallic-7k/",
        "source_label": "PaintScratch 1977 AMC",
        "hex_value": "#0E3566"
      },
      {
        "display_name": "Lime Green",
        "paint_code": "7P",
        "slug": "lime-green-7p",
        "reference_url": "https://www.paintscratch.com/colors/amc/lime-green-7p/",
        "source_label": "PaintScratch 1977 AMC",
        "hex_value": "#3AB537"
      },
      {
        "display_name": "Captain Blue Metallic",
        "paint_code": "7W",
        "slug": "captain-blue-metallic-7w",
        "reference_url": "https://www.paintscratch.com/colors/amc/captain-blue-metallic-7w/",
        "source_label": "PaintScratch 1977 AMC",
        "hex_value": "#67A1AB"
      },
      {
        "display_name": "Tawny Orange",
        "paint_code": "7Y",
        "slug": "tawny-orange-7y",
        "reference_url": "https://www.paintscratch.com/colors/amc/tawny-orange-7y/",
        "source_label": "PaintScratch 1977 AMC",
        "hex_value": "#E36C1D"
      },
      {
        "display_name": "Sun Orange",
        "paint_code": "7Z",
        "slug": "sun-orange-7z",
        "reference_url": "https://www.paintscratch.com/colors/amc/sun-orange-7z/",
        "source_label": "PaintScratch 1977 AMC",
        "hex_value": "#F55101"
      },
      {
        "display_name": "Alpine White",
        "paint_code": "G7",
        "slug": "alpine-white-g7",
        "reference_url": "https://www.paintscratch.com/colors/amc/alpine-white-g7/",
        "source_label": "PaintScratch 1977 AMC",
        "hex_value": "#F9F8E9"
      }
    ],
    "1978": [
      {
        "display_name": "Sand Tan",
        "paint_code": "6D",
        "slug": "sand-tan-6d",
        "reference_url": "https://www.paintscratch.com/colors/amc/sand-tan-6d/",
        "source_label": "PaintScratch 1978 AMC",
        "hex_value": "#C8B380"
      },
      {
        "display_name": "Loden Green Metallic",
        "paint_code": "7L",
        "slug": "loden-green-metallic-7l",
        "reference_url": "https://www.paintscratch.com/colors/amc/loden-green-metallic-7l/",
        "source_label": "PaintScratch 1978 AMC",
        "hex_value": "#38612B"
      },
      {
        "display_name": "Golden Ginger Metallic",
        "paint_code": "7M",
        "slug": "golden-ginger-metallic-7m",
        "reference_url": "https://www.paintscratch.com/colors/amc/golden-ginger-metallic-7m/",
        "source_label": "PaintScratch 1978 AMC",
        "hex_value": "#A37349"
      },
      {
        "display_name": "Firecracker Red",
        "paint_code": "6P",
        "slug": "firecracker-red-6p",
        "reference_url": "https://www.paintscratch.com/colors/amc/firecracker-red-6p/",
        "source_label": "PaintScratch 1978 AMC",
        "hex_value": "#D61616"
      },
      {
        "display_name": "Sunshine Yellow",
        "paint_code": "6V",
        "slug": "sunshine-yellow-6v",
        "reference_url": "https://www.paintscratch.com/colors/amc/sunshine-yellow-6v/",
        "source_label": "PaintScratch 1978 AMC",
        "hex_value": "#F0DD3A"
      },
      {
        "display_name": "Mocha Brown Metallic",
        "paint_code": "7B",
        "slug": "mocha-brown-metallic-7b",
        "reference_url": "https://www.paintscratch.com/colors/amc/mocha-brown-metallic-7b/",
        "source_label": "PaintScratch 1978 AMC",
        "hex_value": "#654419"
      },
      {
        "display_name": "Autumn Red Metallic",
        "paint_code": "7C",
        "slug": "autumn-red-metallic-7c",
        "reference_url": "https://www.paintscratch.com/colors/amc/autumn-red-metallic-7c/",
        "source_label": "PaintScratch 1978 AMC",
        "hex_value": "#A50D14"
      },
      {
        "display_name": "Powder Blue",
        "paint_code": "7D",
        "slug": "powder-blue-7d",
        "reference_url": "https://www.paintscratch.com/colors/amc/powder-blue-7d/",
        "source_label": "PaintScratch 1978 AMC",
        "hex_value": "#9BBFBF"
      },
      {
        "display_name": "Midnight Blue Metallic",
        "paint_code": "7K",
        "slug": "midnight-blue-metallic-7k",
        "reference_url": "https://www.paintscratch.com/colors/amc/midnight-blue-metallic-7k/",
        "source_label": "PaintScratch 1978 AMC",
        "hex_value": "#0E3566"
      },
      {
        "display_name": "Captain Blue Metallic",
        "paint_code": "7W",
        "slug": "captain-blue-metallic-7w",
        "reference_url": "https://www.paintscratch.com/colors/amc/captain-blue-metallic-7w/",
        "source_label": "PaintScratch 1978 AMC",
        "hex_value": "#67A1AB"
      },
      {
        "display_name": "Sun Orange",
        "paint_code": "7Z",
        "slug": "sun-orange-7z",
        "reference_url": "https://www.paintscratch.com/colors/amc/sun-orange-7z/",
        "source_label": "PaintScratch 1978 AMC",
        "hex_value": "#F55101"
      },
      {
        "display_name": "Khaki",
        "paint_code": "8A",
        "slug": "khaki-8a",
        "reference_url": "https://www.paintscratch.com/colors/amc/khaki-8a/",
        "source_label": "PaintScratch 1978 AMC",
        "hex_value": "#AD9E79"
      },
      {
        "display_name": "British Bronze Metallic",
        "paint_code": "8B",
        "slug": "british-bronze-metallic-8b",
        "reference_url": "https://www.paintscratch.com/colors/amc/british-bronze-metallic-8b/",
        "source_label": "PaintScratch 1978 AMC",
        "hex_value": "#958A6F"
      },
      {
        "display_name": "Quicksilver Metallic",
        "paint_code": "8C",
        "slug": "quicksilver-metallic-8c",
        "reference_url": "https://www.paintscratch.com/colors/amc/quicksilver-metallic-8c/",
        "source_label": "PaintScratch 1978 AMC",
        "hex_value": "#C0C0C0"
      },
      {
        "display_name": "Claret Metallic",
        "paint_code": "8D",
        "slug": "claret-metallic-8d",
        "reference_url": "https://www.paintscratch.com/colors/amc/claret-metallic-8d/",
        "source_label": "PaintScratch 1978 AMC",
        "hex_value": "#AB483B"
      },
      {
        "display_name": "Alpine White",
        "paint_code": "G7",
        "slug": "alpine-white-g7",
        "reference_url": "https://www.paintscratch.com/colors/amc/alpine-white-g7/",
        "source_label": "PaintScratch 1978 AMC",
        "hex_value": "#F9F8E9"
      }
    ],
    "1979": [
      {
        "display_name": "Olympic White",
        "paint_code": "9B",
        "slug": "olympic-white-9b",
        "reference_url": "https://www.paintscratch.com/colors/amc/olympic-white-9b/",
        "source_label": "PaintScratch 1979 AMC",
        "hex_value": "#F8F8F2"
      },
      {
        "display_name": "Russet Metallic",
        "paint_code": "9C",
        "slug": "russet-metallic-9c",
        "reference_url": "https://www.paintscratch.com/colors/amc/russet-metallic-9c/",
        "source_label": "PaintScratch 1979 AMC",
        "hex_value": "#B70926"
      },
      {
        "display_name": "Firecracker Red",
        "paint_code": "6P",
        "slug": "firecracker-red-6p",
        "reference_url": "https://www.paintscratch.com/colors/amc/firecracker-red-6p/",
        "source_label": "PaintScratch 1979 AMC",
        "hex_value": "#D61616"
      },
      {
        "display_name": "Khaki",
        "paint_code": "8A",
        "slug": "khaki-8a",
        "reference_url": "https://www.paintscratch.com/colors/amc/khaki-8a/",
        "source_label": "PaintScratch 1979 AMC",
        "hex_value": "#AD9E79"
      },
      {
        "display_name": "British Bronze Metallic",
        "paint_code": "8B",
        "slug": "british-bronze-metallic-8b",
        "reference_url": "https://www.paintscratch.com/colors/amc/british-bronze-metallic-8b/",
        "source_label": "PaintScratch 1979 AMC",
        "hex_value": "#958A6F"
      },
      {
        "display_name": "Quicksilver Metallic",
        "paint_code": "8C",
        "slug": "quicksilver-metallic-8c",
        "reference_url": "https://www.paintscratch.com/colors/amc/quicksilver-metallic-8c/",
        "source_label": "PaintScratch 1979 AMC",
        "hex_value": "#C0C0C0"
      },
      {
        "display_name": "Alpaca Brown Metallic",
        "paint_code": "9A",
        "slug": "alpaca-brown-metallic-9a",
        "reference_url": "https://www.paintscratch.com/colors/amc/alpaca-brown-metallic-9a/",
        "source_label": "PaintScratch 1979 AMC",
        "hex_value": "#89652D"
      },
      {
        "display_name": "Wedgwood Blue",
        "paint_code": "9E",
        "slug": "wedgwood-blue-9e",
        "reference_url": "https://www.paintscratch.com/colors/amc/wedgwood-blue-9e/",
        "source_label": "PaintScratch 1979 AMC",
        "hex_value": "#A9C6CF"
      },
      {
        "display_name": "Cumberland Green Metallic",
        "paint_code": "9H",
        "slug": "cumberland-green-metallic-9h",
        "reference_url": "https://www.paintscratch.com/colors/amc/cumberland-green-metallic-9h/",
        "source_label": "PaintScratch 1979 AMC",
        "hex_value": "#15693F"
      },
      {
        "display_name": "Sable Brown Metallic",
        "paint_code": "9K",
        "slug": "sable-brown-metallic-9k",
        "reference_url": "https://www.paintscratch.com/colors/amc/sable-brown-metallic-9k/",
        "source_label": "PaintScratch 1979 AMC",
        "hex_value": "#785A2C"
      },
      {
        "display_name": "Saxon Yellow",
        "paint_code": "9L",
        "slug": "saxon-yellow-9l",
        "reference_url": "https://www.paintscratch.com/colors/amc/saxon-yellow-9l/",
        "source_label": "PaintScratch 1979 AMC",
        "hex_value": "#F4E45C"
      },
      {
        "display_name": "Starboard Blue Metallic",
        "paint_code": "9M",
        "slug": "starboard-blue-metallic-9m",
        "reference_url": "https://www.paintscratch.com/colors/amc/starboard-blue-metallic-9m/",
        "source_label": "PaintScratch 1979 AMC",
        "hex_value": "#48647E"
      },
      {
        "display_name": "Morocco Buff",
        "paint_code": "9N",
        "slug": "morocco-buff-9n",
        "reference_url": "https://www.paintscratch.com/colors/amc/morocco-buff-9n/",
        "source_label": "PaintScratch 1979 AMC",
        "hex_value": "#EBD1A9"
      },
      {
        "display_name": "Bordeaux Metallic",
        "paint_code": "9P",
        "slug": "bordeaux-metallic-9p",
        "reference_url": "https://www.paintscratch.com/colors/amc/bordeaux-metallic-9p/",
        "source_label": "PaintScratch 1979 AMC",
        "hex_value": "#7F150D"
      },
      {
        "display_name": "Misty Beige Metallic",
        "paint_code": "9Z",
        "slug": "misty-beige-metallic-9z",
        "reference_url": "https://www.paintscratch.com/colors/amc/misty-beige-metallic-9z/",
        "source_label": "PaintScratch 1979 AMC",
        "hex_value": "#A47E52"
      },
      {
        "display_name": "Classic Black",
        "paint_code": "P1",
        "slug": "classic-black-p1",
        "reference_url": "https://www.paintscratch.com/colors/amc/classic-black-p1/",
        "source_label": "PaintScratch 1979 AMC",
        "hex_value": "#000000"
      }
    ],
    "1980": [
      {
        "display_name": "Olympic White",
        "paint_code": "9B",
        "slug": "olympic-white-9b",
        "reference_url": "https://www.paintscratch.com/colors/amc/olympic-white-9b/",
        "source_label": "PaintScratch 1980 AMC",
        "hex_value": "#F8F8F2"
      },
      {
        "display_name": "Russet Metallic",
        "paint_code": "9C",
        "slug": "russet-metallic-9c",
        "reference_url": "https://www.paintscratch.com/colors/amc/russet-metallic-9c/",
        "source_label": "PaintScratch 1980 AMC",
        "hex_value": "#B70926"
      },
      {
        "display_name": "Quicksilver Metallic",
        "paint_code": "8C",
        "slug": "quicksilver-metallic-8c",
        "reference_url": "https://www.paintscratch.com/colors/amc/quicksilver-metallic-8c/",
        "source_label": "PaintScratch 1980 AMC",
        "hex_value": "#C0C0C0"
      },
      {
        "display_name": "Saxon Yellow",
        "paint_code": "9L",
        "slug": "saxon-yellow-9l",
        "reference_url": "https://www.paintscratch.com/colors/amc/saxon-yellow-9l/",
        "source_label": "PaintScratch 1980 AMC",
        "hex_value": "#F4E45C"
      },
      {
        "display_name": "Bordeaux Metallic",
        "paint_code": "9P",
        "slug": "bordeaux-metallic-9p",
        "reference_url": "https://www.paintscratch.com/colors/amc/bordeaux-metallic-9p/",
        "source_label": "PaintScratch 1980 AMC",
        "hex_value": "#7F150D"
      },
      {
        "display_name": "Misty Beige Metallic",
        "paint_code": "9Z",
        "slug": "misty-beige-metallic-9z",
        "reference_url": "https://www.paintscratch.com/colors/amc/misty-beige-metallic-9z/",
        "source_label": "PaintScratch 1980 AMC",
        "hex_value": "#A47E52"
      },
      {
        "display_name": "Smoke Gray Metallic",
        "paint_code": "OB",
        "slug": "smoke-gray-metallic-ob",
        "reference_url": "https://www.paintscratch.com/colors/amc/smoke-gray-metallic-ob/",
        "source_label": "PaintScratch 1980 AMC",
        "hex_value": "#6B6D73"
      },
      {
        "display_name": "Cameo Blue",
        "paint_code": "OC",
        "slug": "cameo-blue-oc",
        "reference_url": "https://www.paintscratch.com/colors/amc/cameo-blue-oc/",
        "source_label": "PaintScratch 1980 AMC",
        "hex_value": "#CFDDE3"
      },
      {
        "display_name": "Medium Blue Metallic",
        "paint_code": "OD",
        "slug": "medium-blue-metallic-od",
        "reference_url": "https://www.paintscratch.com/colors/amc/medium-blue-metallic-od/",
        "source_label": "PaintScratch 1980 AMC",
        "hex_value": "#637D97"
      },
      {
        "display_name": "Dark Green Metallic",
        "paint_code": "OE",
        "slug": "dark-green-metallic-oe",
        "reference_url": "https://www.paintscratch.com/colors/amc/dark-green-metallic-oe/",
        "source_label": "PaintScratch 1980 AMC",
        "hex_value": "#0E5826"
      },
      {
        "display_name": "Navy Blue",
        "paint_code": "OH",
        "slug": "navy-blue-oh",
        "reference_url": "https://www.paintscratch.com/colors/amc/navy-blue-oh/",
        "source_label": "PaintScratch 1980 AMC",
        "hex_value": "#0A2052"
      },
      {
        "display_name": "Cameo Tan",
        "paint_code": "OK",
        "slug": "cameo-tan-ok",
        "reference_url": "https://www.paintscratch.com/colors/amc/cameo-tan-ok/",
        "source_label": "PaintScratch 1980 AMC",
        "hex_value": "#C6AB6A"
      },
      {
        "display_name": "Medium Brown Metallic",
        "paint_code": "OL",
        "slug": "medium-brown-metallic-ol",
        "reference_url": "https://www.paintscratch.com/colors/amc/medium-brown-metallic-ol/",
        "source_label": "PaintScratch 1980 AMC",
        "hex_value": "#8C633A"
      },
      {
        "display_name": "Dark Brown Metallic",
        "paint_code": "OM",
        "slug": "dark-brown-metallic-om",
        "reference_url": "https://www.paintscratch.com/colors/amc/dark-brown-metallic-om/",
        "source_label": "PaintScratch 1980 AMC",
        "hex_value": "#564236"
      },
      {
        "display_name": "Cardinal Red",
        "paint_code": "OP",
        "slug": "cardinal-red-op",
        "reference_url": "https://www.paintscratch.com/colors/amc/cardinal-red-op/",
        "source_label": "PaintScratch 1980 AMC",
        "hex_value": "#C01818"
      },
      {
        "display_name": "Caramel",
        "paint_code": "OR",
        "slug": "caramel-or",
        "reference_url": "https://www.paintscratch.com/colors/amc/caramel-or/",
        "source_label": "PaintScratch 1980 AMC",
        "hex_value": "#BB6E23"
      }
    ],
    "1981": [
      {
        "display_name": "Sherwood Green Metallic",
        "paint_code": "1C",
        "slug": "sherwood-green-metallic-1c",
        "reference_url": "https://www.paintscratch.com/colors/amc/sherwood-green-metallic-1c/",
        "source_label": "PaintScratch 1981 AMC",
        "hex_value": "#3D582E"
      },
      {
        "display_name": "Copper Brown Metallic",
        "paint_code": "1E",
        "slug": "copper-brown-metallic-1e",
        "reference_url": "https://www.paintscratch.com/colors/amc/copper-brown-metallic-1e/",
        "source_label": "PaintScratch 1981 AMC",
        "hex_value": "#D97F43"
      },
      {
        "display_name": "Olympic White",
        "paint_code": "9B",
        "slug": "olympic-white-9b",
        "reference_url": "https://www.paintscratch.com/colors/amc/olympic-white-9b/",
        "source_label": "PaintScratch 1981 AMC",
        "hex_value": "#F8F8F2"
      },
      {
        "display_name": "Moonlight Blue",
        "paint_code": "1B",
        "slug": "moonlight-blue-1b",
        "reference_url": "https://www.paintscratch.com/colors/amc/moonlight-blue-1b/",
        "source_label": "PaintScratch 1981 AMC",
        "hex_value": "#0E2B5C"
      },
      {
        "display_name": "Autumn Gold",
        "paint_code": "1D",
        "slug": "autumn-gold-1d",
        "reference_url": "https://www.paintscratch.com/colors/amc/autumn-gold-1d/",
        "source_label": "PaintScratch 1981 AMC",
        "hex_value": "#C1B46F"
      },
      {
        "display_name": "Vintage Red Metallic",
        "paint_code": "1J",
        "slug": "vintage-red-metallic-1j",
        "reference_url": "https://www.paintscratch.com/colors/amc/vintage-red-metallic-1j/",
        "source_label": "PaintScratch 1981 AMC",
        "hex_value": "#AF221F"
      },
      {
        "display_name": "Deep Maroon Metallic",
        "paint_code": "1K",
        "slug": "deep-maroon-metallic-1k",
        "reference_url": "https://www.paintscratch.com/colors/amc/deep-maroon-metallic-1k/",
        "source_label": "PaintScratch 1981 AMC",
        "hex_value": "#801E1E"
      },
      {
        "display_name": "Steel Gray Metallic",
        "paint_code": "1L",
        "slug": "steel-gray-metallic-1l",
        "reference_url": "https://www.paintscratch.com/colors/amc/steel-gray-metallic-1l/",
        "source_label": "PaintScratch 1981 AMC",
        "hex_value": "#808080"
      },
      {
        "display_name": "Oriental Red",
        "paint_code": "1M",
        "slug": "oriental-red-1m",
        "reference_url": "https://www.paintscratch.com/colors/amc/oriental-red-1m/",
        "source_label": "PaintScratch 1981 AMC",
        "hex_value": "#AB1B1B"
      },
      {
        "display_name": "Quicksilver Metallic",
        "paint_code": "8C",
        "slug": "quicksilver-metallic-8c",
        "reference_url": "https://www.paintscratch.com/colors/amc/quicksilver-metallic-8c/",
        "source_label": "PaintScratch 1981 AMC",
        "hex_value": "#C0C0C0"
      },
      {
        "display_name": "Medium Blue Metallic",
        "paint_code": "OD",
        "slug": "medium-blue-metallic-od",
        "reference_url": "https://www.paintscratch.com/colors/amc/medium-blue-metallic-od/",
        "source_label": "PaintScratch 1981 AMC",
        "hex_value": "#637D97"
      },
      {
        "display_name": "Cameo Tan",
        "paint_code": "OK",
        "slug": "cameo-tan-ok",
        "reference_url": "https://www.paintscratch.com/colors/amc/cameo-tan-ok/",
        "source_label": "PaintScratch 1981 AMC",
        "hex_value": "#C6AB6A"
      },
      {
        "display_name": "Medium Brown Metallic",
        "paint_code": "OL",
        "slug": "medium-brown-metallic-ol",
        "reference_url": "https://www.paintscratch.com/colors/amc/medium-brown-metallic-ol/",
        "source_label": "PaintScratch 1981 AMC",
        "hex_value": "#8C633A"
      },
      {
        "display_name": "Dark Brown Metallic",
        "paint_code": "OM",
        "slug": "dark-brown-metallic-om",
        "reference_url": "https://www.paintscratch.com/colors/amc/dark-brown-metallic-om/",
        "source_label": "PaintScratch 1981 AMC",
        "hex_value": "#564236"
      },
      {
        "display_name": "Classic Black",
        "paint_code": "P1",
        "slug": "classic-black-p1",
        "reference_url": "https://www.paintscratch.com/colors/amc/classic-black-p1/",
        "source_label": "PaintScratch 1981 AMC",
        "hex_value": "#000000"
      }
    ],
    "1982": [
      {
        "display_name": "Sherwood Green Metallic",
        "paint_code": "1C",
        "slug": "sherwood-green-metallic-1c",
        "reference_url": "https://www.paintscratch.com/colors/amc/sherwood-green-metallic-1c/",
        "source_label": "PaintScratch 1982 AMC",
        "hex_value": "#3D582E"
      },
      {
        "display_name": "Copper Brown Metallic",
        "paint_code": "1E",
        "slug": "copper-brown-metallic-1e",
        "reference_url": "https://www.paintscratch.com/colors/amc/copper-brown-metallic-1e/",
        "source_label": "PaintScratch 1982 AMC",
        "hex_value": "#D97F43"
      },
      {
        "display_name": "Olympic White",
        "paint_code": "9B",
        "slug": "olympic-white-9b",
        "reference_url": "https://www.paintscratch.com/colors/amc/olympic-white-9b/",
        "source_label": "PaintScratch 1982 AMC",
        "hex_value": "#F8F8F2"
      },
      {
        "display_name": "Dark Brown Metallic",
        "paint_code": "0M",
        "slug": "dark-brown-metallic-0m",
        "reference_url": "https://www.paintscratch.com/colors/amc/dark-brown-metallic-0m/",
        "source_label": "PaintScratch 1982 AMC",
        "hex_value": "#77522D"
      },
      {
        "display_name": "Vintage Red Metallic",
        "paint_code": "1J",
        "slug": "vintage-red-metallic-1j",
        "reference_url": "https://www.paintscratch.com/colors/amc/vintage-red-metallic-1j/",
        "source_label": "PaintScratch 1982 AMC",
        "hex_value": "#AF221F"
      },
      {
        "display_name": "Deep Maroon Metallic",
        "paint_code": "1K",
        "slug": "deep-maroon-metallic-1k",
        "reference_url": "https://www.paintscratch.com/colors/amc/deep-maroon-metallic-1k/",
        "source_label": "PaintScratch 1982 AMC",
        "hex_value": "#801E1E"
      },
      {
        "display_name": "Oriental Red",
        "paint_code": "1M",
        "slug": "oriental-red-1m",
        "reference_url": "https://www.paintscratch.com/colors/amc/oriental-red-1m/",
        "source_label": "PaintScratch 1982 AMC",
        "hex_value": "#AB1B1B"
      },
      {
        "display_name": "Mist Silver Metallic",
        "paint_code": "2A",
        "slug": "mist-silver-metallic-2a",
        "reference_url": "https://www.paintscratch.com/colors/amc/mist-silver-metallic-2a/",
        "source_label": "PaintScratch 1982 AMC",
        "hex_value": "#DADDE0"
      },
      {
        "display_name": "Sun Yellow",
        "paint_code": "2B",
        "slug": "sun-yellow-2b",
        "reference_url": "https://www.paintscratch.com/colors/amc/sun-yellow-2b/",
        "source_label": "PaintScratch 1982 AMC",
        "hex_value": "#FACE00"
      },
      {
        "display_name": "Slate Blue Metallic",
        "paint_code": "2C",
        "slug": "slate-blue-metallic-2c",
        "reference_url": "https://www.paintscratch.com/colors/amc/slate-blue-metallic-2c/",
        "source_label": "PaintScratch 1982 AMC",
        "hex_value": "#6A8396"
      },
      {
        "display_name": "Deep Night Blue",
        "paint_code": "2D",
        "slug": "deep-night-blue-2d",
        "reference_url": "https://www.paintscratch.com/colors/amc/deep-night-blue-2d/",
        "source_label": "PaintScratch 1982 AMC",
        "hex_value": "#173145"
      },
      {
        "display_name": "Sea Blue Metallic",
        "paint_code": "2E",
        "slug": "sea-blue-metallic-2e",
        "reference_url": "https://www.paintscratch.com/colors/amc/sea-blue-metallic-2e/",
        "source_label": "PaintScratch 1982 AMC",
        "hex_value": "#1D7D58"
      },
      {
        "display_name": "Topaz Gold Metallic",
        "paint_code": "2H",
        "slug": "topaz-gold-metallic-2h",
        "reference_url": "https://www.paintscratch.com/colors/amc/topaz-gold-metallic-2h/",
        "source_label": "PaintScratch 1982 AMC",
        "hex_value": "#D39A3F"
      },
      {
        "display_name": "Jamaican Beige",
        "paint_code": "2J",
        "slug": "jamaican-beige-2j",
        "reference_url": "https://www.paintscratch.com/colors/amc/jamaican-beige-2j/",
        "source_label": "PaintScratch 1982 AMC",
        "hex_value": "#E9DBAB"
      },
      {
        "display_name": "Classic Black",
        "paint_code": "P1",
        "slug": "classic-black-p1",
        "reference_url": "https://www.paintscratch.com/colors/amc/classic-black-p1/",
        "source_label": "PaintScratch 1982 AMC",
        "hex_value": "#000000"
      }
    ],
    "1983": [
      {
        "display_name": "Copper Brown Metallic",
        "paint_code": "1E",
        "slug": "copper-brown-metallic-1e",
        "reference_url": "https://www.paintscratch.com/colors/amc/copper-brown-metallic-1e/",
        "source_label": "PaintScratch 1983 AMC",
        "hex_value": "#D97F43"
      },
      {
        "display_name": "Olympic White",
        "paint_code": "9B",
        "slug": "olympic-white-9b",
        "reference_url": "https://www.paintscratch.com/colors/amc/olympic-white-9b/",
        "source_label": "PaintScratch 1983 AMC",
        "hex_value": "#F8F8F2"
      },
      {
        "display_name": "Dark Brown Metallic",
        "paint_code": "0M",
        "slug": "dark-brown-metallic-0m",
        "reference_url": "https://www.paintscratch.com/colors/amc/dark-brown-metallic-0m/",
        "source_label": "PaintScratch 1983 AMC",
        "hex_value": "#77522D"
      },
      {
        "display_name": "Low Gloss Black Accent Color",
        "paint_code": "0T",
        "slug": "low-gloss-black-accent-color-0t",
        "reference_url": "https://www.paintscratch.com/colors/amc/low-gloss-black-accent-color-0t/",
        "source_label": "PaintScratch 1983 AMC",
        "hex_value": "#000000"
      },
      {
        "display_name": "Vintage Red Metallic",
        "paint_code": "1J",
        "slug": "vintage-red-metallic-1j",
        "reference_url": "https://www.paintscratch.com/colors/amc/vintage-red-metallic-1j/",
        "source_label": "PaintScratch 1983 AMC",
        "hex_value": "#AF221F"
      },
      {
        "display_name": "Deep Maroon Metallic",
        "paint_code": "1K",
        "slug": "deep-maroon-metallic-1k",
        "reference_url": "https://www.paintscratch.com/colors/amc/deep-maroon-metallic-1k/",
        "source_label": "PaintScratch 1983 AMC",
        "hex_value": "#801E1E"
      },
      {
        "display_name": "Mist Silver Metallic",
        "paint_code": "2A",
        "slug": "mist-silver-metallic-2a",
        "reference_url": "https://www.paintscratch.com/colors/amc/mist-silver-metallic-2a/",
        "source_label": "PaintScratch 1983 AMC",
        "hex_value": "#DADDE0"
      },
      {
        "display_name": "Slate Blue Metallic",
        "paint_code": "2C",
        "slug": "slate-blue-metallic-2c",
        "reference_url": "https://www.paintscratch.com/colors/amc/slate-blue-metallic-2c/",
        "source_label": "PaintScratch 1983 AMC",
        "hex_value": "#6A8396"
      },
      {
        "display_name": "Deep Night Blue",
        "paint_code": "2D",
        "slug": "deep-night-blue-2d",
        "reference_url": "https://www.paintscratch.com/colors/amc/deep-night-blue-2d/",
        "source_label": "PaintScratch 1983 AMC",
        "hex_value": "#173145"
      },
      {
        "display_name": "Topaz Gold Metallic",
        "paint_code": "2H",
        "slug": "topaz-gold-metallic-2h",
        "reference_url": "https://www.paintscratch.com/colors/amc/topaz-gold-metallic-2h/",
        "source_label": "PaintScratch 1983 AMC",
        "hex_value": "#D39A3F"
      },
      {
        "display_name": "Jamaican Beige",
        "paint_code": "2J",
        "slug": "jamaican-beige-2j",
        "reference_url": "https://www.paintscratch.com/colors/amc/jamaican-beige-2j/",
        "source_label": "PaintScratch 1983 AMC",
        "hex_value": "#E9DBAB"
      },
      {
        "display_name": "Sebring Red",
        "paint_code": "3B",
        "slug": "sebring-red-3b",
        "reference_url": "https://www.paintscratch.com/colors/amc/sebring-red-3b/",
        "source_label": "PaintScratch 1983 AMC",
        "hex_value": "#BB1D1D"
      },
      {
        "display_name": "Diamond Blue Metallic",
        "paint_code": "3H",
        "slug": "diamond-blue-metallic-3h",
        "reference_url": "https://www.paintscratch.com/colors/amc/diamond-blue-metallic-3h/",
        "source_label": "PaintScratch 1983 AMC",
        "hex_value": "#9BB9C5"
      },
      {
        "display_name": "Classic Black",
        "paint_code": "P1",
        "slug": "classic-black-p1",
        "reference_url": "https://www.paintscratch.com/colors/amc/classic-black-p1/",
        "source_label": "PaintScratch 1983 AMC",
        "hex_value": "#000000"
      }
    ],
    "1984": [
      {
        "display_name": "Autumn Brown Metallic",
        "paint_code": "4A",
        "slug": "autumn-brown-metallic-4a",
        "reference_url": "https://www.paintscratch.com/colors/amc/autumn-brown-metallic-4a/",
        "source_label": "PaintScratch 1984 AMC",
        "hex_value": "#B47316"
      },
      {
        "display_name": "Olympic White",
        "paint_code": "9B",
        "slug": "olympic-white-9b",
        "reference_url": "https://www.paintscratch.com/colors/amc/olympic-white-9b/",
        "source_label": "PaintScratch 1984 AMC",
        "hex_value": "#F8F8F2"
      },
      {
        "display_name": "Low Gloss Black Accent Color",
        "paint_code": "0T",
        "slug": "low-gloss-black-accent-color-0t",
        "reference_url": "https://www.paintscratch.com/colors/amc/low-gloss-black-accent-color-0t/",
        "source_label": "PaintScratch 1984 AMC",
        "hex_value": "#000000"
      },
      {
        "display_name": "Mist Silver Metallic",
        "paint_code": "2A",
        "slug": "mist-silver-metallic-2a",
        "reference_url": "https://www.paintscratch.com/colors/amc/mist-silver-metallic-2a/",
        "source_label": "PaintScratch 1984 AMC",
        "hex_value": "#DADDE0"
      },
      {
        "display_name": "Slate Blue Metallic",
        "paint_code": "2C",
        "slug": "slate-blue-metallic-2c",
        "reference_url": "https://www.paintscratch.com/colors/amc/slate-blue-metallic-2c/",
        "source_label": "PaintScratch 1984 AMC",
        "hex_value": "#6A8396"
      },
      {
        "display_name": "Deep Night Blue",
        "paint_code": "2D",
        "slug": "deep-night-blue-2d",
        "reference_url": "https://www.paintscratch.com/colors/amc/deep-night-blue-2d/",
        "source_label": "PaintScratch 1984 AMC",
        "hex_value": "#173145"
      },
      {
        "display_name": "Topaz Gold Metallic",
        "paint_code": "2H",
        "slug": "topaz-gold-metallic-2h",
        "reference_url": "https://www.paintscratch.com/colors/amc/topaz-gold-metallic-2h/",
        "source_label": "PaintScratch 1984 AMC",
        "hex_value": "#D39A3F"
      },
      {
        "display_name": "Almond Beige",
        "paint_code": "3A",
        "slug": "almond-beige-3a",
        "reference_url": "https://www.paintscratch.com/colors/amc/almond-beige-3a/",
        "source_label": "PaintScratch 1984 AMC",
        "hex_value": "#D3CBB3"
      },
      {
        "display_name": "Sebring Red",
        "paint_code": "3B",
        "slug": "sebring-red-3b",
        "reference_url": "https://www.paintscratch.com/colors/amc/sebring-red-3b/",
        "source_label": "PaintScratch 1984 AMC",
        "hex_value": "#BB1D1D"
      },
      {
        "display_name": "Garnet Metallic",
        "paint_code": "3P",
        "slug": "garnet-metallic-3p",
        "reference_url": "https://www.paintscratch.com/colors/amc/garnet-metallic-3p/",
        "source_label": "PaintScratch 1984 AMC",
        "hex_value": "#B41616"
      },
      {
        "display_name": "Mocha Dark Brown Metallic",
        "paint_code": "4B",
        "slug": "mocha-dark-brown-metallic-4b",
        "reference_url": "https://www.paintscratch.com/colors/amc/mocha-dark-brown-metallic-4b/",
        "source_label": "PaintScratch 1984 AMC",
        "hex_value": "#985F28"
      },
      {
        "display_name": "Classic Black",
        "paint_code": "P1",
        "slug": "classic-black-p1",
        "reference_url": "https://www.paintscratch.com/colors/amc/classic-black-p1/",
        "source_label": "PaintScratch 1984 AMC",
        "hex_value": "#000000"
      }
    ],
    "1985": [
      {
        "display_name": "Autumn Brown Metallic",
        "paint_code": "4A",
        "slug": "autumn-brown-metallic-4a",
        "reference_url": "https://www.paintscratch.com/colors/amc/autumn-brown-metallic-4a/",
        "source_label": "PaintScratch 1985 AMC",
        "hex_value": "#B47316"
      },
      {
        "display_name": "Olympic White",
        "paint_code": "9B",
        "slug": "olympic-white-9b",
        "reference_url": "https://www.paintscratch.com/colors/amc/olympic-white-9b/",
        "source_label": "PaintScratch 1985 AMC",
        "hex_value": "#F8F8F2"
      },
      {
        "display_name": "Low Gloss Black Accent Color",
        "paint_code": "0T",
        "slug": "low-gloss-black-accent-color-0t",
        "reference_url": "https://www.paintscratch.com/colors/amc/low-gloss-black-accent-color-0t/",
        "source_label": "PaintScratch 1985 AMC",
        "hex_value": "#000000"
      },
      {
        "display_name": "Mist Silver Metallic",
        "paint_code": "2A",
        "slug": "mist-silver-metallic-2a",
        "reference_url": "https://www.paintscratch.com/colors/amc/mist-silver-metallic-2a/",
        "source_label": "PaintScratch 1985 AMC",
        "hex_value": "#DADDE0"
      },
      {
        "display_name": "Almond Beige",
        "paint_code": "3A",
        "slug": "almond-beige-3a",
        "reference_url": "https://www.paintscratch.com/colors/amc/almond-beige-3a/",
        "source_label": "PaintScratch 1985 AMC",
        "hex_value": "#D3CBB3"
      },
      {
        "display_name": "Sebring Red",
        "paint_code": "3B",
        "slug": "sebring-red-3b",
        "reference_url": "https://www.paintscratch.com/colors/amc/sebring-red-3b/",
        "source_label": "PaintScratch 1985 AMC",
        "hex_value": "#BB1D1D"
      },
      {
        "display_name": "Sterling Metallic",
        "paint_code": "3D",
        "slug": "sterling-metallic-3d",
        "reference_url": "https://www.paintscratch.com/colors/amc/sterling-metallic-3d/",
        "source_label": "PaintScratch 1985 AMC",
        "hex_value": "#D9DDE1"
      },
      {
        "display_name": "Garnet Metallic",
        "paint_code": "3P",
        "slug": "garnet-metallic-3p",
        "reference_url": "https://www.paintscratch.com/colors/amc/garnet-metallic-3p/",
        "source_label": "PaintScratch 1985 AMC",
        "hex_value": "#B41616"
      },
      {
        "display_name": "Mocha Dark Brown Metallic",
        "paint_code": "4B",
        "slug": "mocha-dark-brown-metallic-4b",
        "reference_url": "https://www.paintscratch.com/colors/amc/mocha-dark-brown-metallic-4b/",
        "source_label": "PaintScratch 1985 AMC",
        "hex_value": "#985F28"
      },
      {
        "display_name": "Florentine Gold Metallic",
        "paint_code": "4J",
        "slug": "florentine-gold-metallic-4j",
        "reference_url": "https://www.paintscratch.com/colors/amc/florentine-gold-metallic-4j/",
        "source_label": "PaintScratch 1985 AMC",
        "hex_value": "#C1882F"
      },
      {
        "display_name": "Adriatic Blue Pearl Metallic",
        "paint_code": "4L",
        "slug": "adriatic-blue-pearl-metallic-4l",
        "reference_url": "https://www.paintscratch.com/colors/amc/adriatic-blue-pearl-metallic-4l/",
        "source_label": "PaintScratch 1985 AMC",
        "hex_value": "#7594AB"
      },
      {
        "display_name": "Charcoal Metallic",
        "paint_code": "4M",
        "slug": "charcoal-metallic-4m",
        "reference_url": "https://www.paintscratch.com/colors/amc/charcoal-metallic-4m/",
        "source_label": "PaintScratch 1985 AMC",
        "hex_value": "#69645D"
      },
      {
        "display_name": "Light Blue Metallic",
        "paint_code": "5A",
        "slug": "light-blue-metallic-5a",
        "reference_url": "https://www.paintscratch.com/colors/amc/light-blue-metallic-5a/",
        "source_label": "PaintScratch 1985 AMC",
        "hex_value": "#AAC1CE"
      },
      {
        "display_name": "Medium Green Metallic",
        "paint_code": "5B",
        "slug": "medium-green-metallic-5b",
        "reference_url": "https://www.paintscratch.com/colors/amc/medium-green-metallic-5b/",
        "source_label": "PaintScratch 1985 AMC",
        "hex_value": "#758864"
      },
      {
        "display_name": "Red Metallic",
        "paint_code": "5C",
        "slug": "red-metallic-5c",
        "reference_url": "https://www.paintscratch.com/colors/amc/red-metallic-5c/",
        "source_label": "PaintScratch 1985 AMC",
        "hex_value": "#BB2323"
      },
      {
        "display_name": "Medium Blue Metallic",
        "paint_code": "5H",
        "slug": "medium-blue-metallic-5h",
        "reference_url": "https://www.paintscratch.com/colors/amc/medium-blue-metallic-5h/",
        "source_label": "PaintScratch 1985 AMC",
        "hex_value": "#6295A6"
      }
    ],
    "1986": [
      {
        "display_name": "Autumn Brown Metallic",
        "paint_code": "4A",
        "slug": "autumn-brown-metallic-4a",
        "reference_url": "https://www.paintscratch.com/colors/amc/autumn-brown-metallic-4a/",
        "source_label": "PaintScratch 1986 AMC",
        "hex_value": "#B47316"
      },
      {
        "display_name": "Olympic White",
        "paint_code": "9B",
        "slug": "olympic-white-9b",
        "reference_url": "https://www.paintscratch.com/colors/amc/olympic-white-9b/",
        "source_label": "PaintScratch 1986 AMC",
        "hex_value": "#F8F8F2"
      },
      {
        "display_name": "Low Gloss Black Accent Color",
        "paint_code": "0T",
        "slug": "low-gloss-black-accent-color-0t",
        "reference_url": "https://www.paintscratch.com/colors/amc/low-gloss-black-accent-color-0t/",
        "source_label": "PaintScratch 1986 AMC",
        "hex_value": "#000000"
      },
      {
        "display_name": "Mist Silver Metallic",
        "paint_code": "2A",
        "slug": "mist-silver-metallic-2a",
        "reference_url": "https://www.paintscratch.com/colors/amc/mist-silver-metallic-2a/",
        "source_label": "PaintScratch 1986 AMC",
        "hex_value": "#DADDE0"
      },
      {
        "display_name": "Sebring Red",
        "paint_code": "3B",
        "slug": "sebring-red-3b",
        "reference_url": "https://www.paintscratch.com/colors/amc/sebring-red-3b/",
        "source_label": "PaintScratch 1986 AMC",
        "hex_value": "#BB1D1D"
      },
      {
        "display_name": "Sterling Metallic",
        "paint_code": "3D",
        "slug": "sterling-metallic-3d",
        "reference_url": "https://www.paintscratch.com/colors/amc/sterling-metallic-3d/",
        "source_label": "PaintScratch 1986 AMC",
        "hex_value": "#D9DDE1"
      },
      {
        "display_name": "Garnet Metallic",
        "paint_code": "3P",
        "slug": "garnet-metallic-3p",
        "reference_url": "https://www.paintscratch.com/colors/amc/garnet-metallic-3p/",
        "source_label": "PaintScratch 1986 AMC",
        "hex_value": "#B41616"
      },
      {
        "display_name": "Mocha Dark Brown Metallic",
        "paint_code": "4B",
        "slug": "mocha-dark-brown-metallic-4b",
        "reference_url": "https://www.paintscratch.com/colors/amc/mocha-dark-brown-metallic-4b/",
        "source_label": "PaintScratch 1986 AMC",
        "hex_value": "#985F28"
      },
      {
        "display_name": "Light Blue Metallic",
        "paint_code": "5A",
        "slug": "light-blue-metallic-5a",
        "reference_url": "https://www.paintscratch.com/colors/amc/light-blue-metallic-5a/",
        "source_label": "PaintScratch 1986 AMC",
        "hex_value": "#AAC1CE"
      },
      {
        "display_name": "Medium Green Metallic",
        "paint_code": "5B",
        "slug": "medium-green-metallic-5b",
        "reference_url": "https://www.paintscratch.com/colors/amc/medium-green-metallic-5b/",
        "source_label": "PaintScratch 1986 AMC",
        "hex_value": "#758864"
      },
      {
        "display_name": "Red Metallic",
        "paint_code": "5C",
        "slug": "red-metallic-5c",
        "reference_url": "https://www.paintscratch.com/colors/amc/red-metallic-5c/",
        "source_label": "PaintScratch 1986 AMC",
        "hex_value": "#BB2323"
      },
      {
        "display_name": "Medium Blue Metallic",
        "paint_code": "5H",
        "slug": "medium-blue-metallic-5h",
        "reference_url": "https://www.paintscratch.com/colors/amc/medium-blue-metallic-5h/",
        "source_label": "PaintScratch 1986 AMC",
        "hex_value": "#6295A6"
      },
      {
        "display_name": "Dark Blue Metallic",
        "paint_code": "5J",
        "slug": "dark-blue-metallic-5j",
        "reference_url": "https://www.paintscratch.com/colors/amc/dark-blue-metallic-5j/",
        "source_label": "PaintScratch 1986 AMC",
        "hex_value": "#142C4C"
      },
      {
        "display_name": "Dark Pewter Metallic",
        "paint_code": "AA",
        "slug": "dark-pewter-metallic-aa",
        "reference_url": "https://www.paintscratch.com/colors/amc/dark-pewter-metallic-aa/",
        "source_label": "PaintScratch 1986 AMC",
        "hex_value": "#A5A593"
      },
      {
        "display_name": "Beige",
        "paint_code": "AB",
        "slug": "beige-ab",
        "reference_url": "https://www.paintscratch.com/colors/amc/beige-ab/",
        "source_label": "PaintScratch 1986 AMC",
        "hex_value": "#F2EDCE"
      },
      {
        "display_name": "Gold Metallic",
        "paint_code": "AC",
        "slug": "gold-metallic-ac",
        "reference_url": "https://www.paintscratch.com/colors/amc/gold-metallic-ac/",
        "source_label": "PaintScratch 1986 AMC",
        "hex_value": "#D6A662"
      }
    ],
    "1987": [
      {
        "display_name": "Autumn Brown Metallic",
        "paint_code": "4A",
        "slug": "autumn-brown-metallic-4a",
        "reference_url": "https://www.paintscratch.com/colors/amc/autumn-brown-metallic-4a/",
        "source_label": "PaintScratch 1987 AMC",
        "hex_value": "#B47316"
      },
      {
        "display_name": "Olympic White",
        "paint_code": "9B",
        "slug": "olympic-white-9b",
        "reference_url": "https://www.paintscratch.com/colors/amc/olympic-white-9b/",
        "source_label": "PaintScratch 1987 AMC",
        "hex_value": "#F8F8F2"
      },
      {
        "display_name": "Mist Silver Metallic",
        "paint_code": "2A",
        "slug": "mist-silver-metallic-2a",
        "reference_url": "https://www.paintscratch.com/colors/amc/mist-silver-metallic-2a/",
        "source_label": "PaintScratch 1987 AMC",
        "hex_value": "#DADDE0"
      },
      {
        "display_name": "Sebring Red",
        "paint_code": "3B",
        "slug": "sebring-red-3b",
        "reference_url": "https://www.paintscratch.com/colors/amc/sebring-red-3b/",
        "source_label": "PaintScratch 1987 AMC",
        "hex_value": "#BB1D1D"
      },
      {
        "display_name": "Sterling Metallic",
        "paint_code": "3D",
        "slug": "sterling-metallic-3d",
        "reference_url": "https://www.paintscratch.com/colors/amc/sterling-metallic-3d/",
        "source_label": "PaintScratch 1987 AMC",
        "hex_value": "#D9DDE1"
      },
      {
        "display_name": "Garnet Metallic",
        "paint_code": "3P",
        "slug": "garnet-metallic-3p",
        "reference_url": "https://www.paintscratch.com/colors/amc/garnet-metallic-3p/",
        "source_label": "PaintScratch 1987 AMC",
        "hex_value": "#B41616"
      },
      {
        "display_name": "Mocha Dark Brown Metallic",
        "paint_code": "4B",
        "slug": "mocha-dark-brown-metallic-4b",
        "reference_url": "https://www.paintscratch.com/colors/amc/mocha-dark-brown-metallic-4b/",
        "source_label": "PaintScratch 1987 AMC",
        "hex_value": "#985F28"
      },
      {
        "display_name": "Champagne Metallic",
        "paint_code": "4D",
        "slug": "champagne-metallic-4d",
        "reference_url": "https://www.paintscratch.com/colors/amc/champagne-metallic-4d/",
        "source_label": "PaintScratch 1987 AMC",
        "hex_value": "#EAC288"
      },
      {
        "display_name": "Light Blue Metallic",
        "paint_code": "5A",
        "slug": "light-blue-metallic-5a",
        "reference_url": "https://www.paintscratch.com/colors/amc/light-blue-metallic-5a/",
        "source_label": "PaintScratch 1987 AMC",
        "hex_value": "#AAC1CE"
      },
      {
        "display_name": "Red Metallic",
        "paint_code": "5C",
        "slug": "red-metallic-5c",
        "reference_url": "https://www.paintscratch.com/colors/amc/red-metallic-5c/",
        "source_label": "PaintScratch 1987 AMC",
        "hex_value": "#BB2323"
      },
      {
        "display_name": "Medium Blue Metallic",
        "paint_code": "5H",
        "slug": "medium-blue-metallic-5h",
        "reference_url": "https://www.paintscratch.com/colors/amc/medium-blue-metallic-5h/",
        "source_label": "PaintScratch 1987 AMC",
        "hex_value": "#6295A6"
      },
      {
        "display_name": "Dark Blue Metallic",
        "paint_code": "5J",
        "slug": "dark-blue-metallic-5j",
        "reference_url": "https://www.paintscratch.com/colors/amc/dark-blue-metallic-5j/",
        "source_label": "PaintScratch 1987 AMC",
        "hex_value": "#142C4C"
      },
      {
        "display_name": "Dark Pewter Metallic",
        "paint_code": "AA",
        "slug": "dark-pewter-metallic-aa",
        "reference_url": "https://www.paintscratch.com/colors/amc/dark-pewter-metallic-aa/",
        "source_label": "PaintScratch 1987 AMC",
        "hex_value": "#A5A593"
      },
      {
        "display_name": "Beige",
        "paint_code": "AB",
        "slug": "beige-ab",
        "reference_url": "https://www.paintscratch.com/colors/amc/beige-ab/",
        "source_label": "PaintScratch 1987 AMC",
        "hex_value": "#F2EDCE"
      },
      {
        "display_name": "Orange Bronze Metallic",
        "paint_code": "AD",
        "slug": "orange-bronze-metallic-ad",
        "reference_url": "https://www.paintscratch.com/colors/amc/orange-bronze-metallic-ad/",
        "source_label": "PaintScratch 1987 AMC",
        "hex_value": "#DC8632"
      },
      {
        "display_name": "Classic Black",
        "paint_code": "P1",
        "slug": "classic-black-p1",
        "reference_url": "https://www.paintscratch.com/colors/amc/classic-black-p1/",
        "source_label": "PaintScratch 1987 AMC",
        "hex_value": "#000000"
      }
    ],
    "1988": [
      {
        "display_name": "Mocha Dark Brown Metallic",
        "paint_code": "4B",
        "slug": "mocha-dark-brown-metallic-4b",
        "reference_url": "https://www.paintscratch.com/colors/amc/mocha-dark-brown-metallic-4b/",
        "source_label": "PaintScratch 1988 AMC",
        "hex_value": "#985F28"
      },
      {
        "display_name": "Dark Blue Metallic",
        "paint_code": "5J",
        "slug": "dark-blue-metallic-5j",
        "reference_url": "https://www.paintscratch.com/colors/amc/dark-blue-metallic-5j/",
        "source_label": "PaintScratch 1988 AMC",
        "hex_value": "#142C4C"
      },
      {
        "display_name": "Beige",
        "paint_code": "AB",
        "slug": "beige-ab",
        "reference_url": "https://www.paintscratch.com/colors/amc/beige-ab/",
        "source_label": "PaintScratch 1988 AMC",
        "hex_value": "#F2EDCE"
      },
      {
        "display_name": "Silver Metallic",
        "paint_code": "BH",
        "slug": "silver-metallic-bh",
        "reference_url": "https://www.paintscratch.com/colors/amc/silver-metallic-bh/",
        "source_label": "PaintScratch 1988 AMC",
        "hex_value": "#D9DDE1"
      },
      {
        "display_name": "Vivid Red Metallic",
        "paint_code": "BK",
        "slug": "vivid-red-metallic-bk",
        "reference_url": "https://www.paintscratch.com/colors/amc/vivid-red-metallic-bk/",
        "source_label": "PaintScratch 1988 AMC",
        "hex_value": "#934729"
      },
      {
        "display_name": "Ice Blue Metallic",
        "paint_code": "BP",
        "slug": "ice-blue-metallic-bp",
        "reference_url": "https://www.paintscratch.com/colors/amc/ice-blue-metallic-bp/",
        "source_label": "PaintScratch 1988 AMC",
        "hex_value": "#B2CACE"
      },
      {
        "display_name": "Silver Metallic",
        "paint_code": "BT",
        "slug": "silver-metallic-bt",
        "reference_url": "https://www.paintscratch.com/colors/amc/silver-metallic-bt/",
        "source_label": "PaintScratch 1988 AMC",
        "hex_value": "#D9DDE1"
      },
      {
        "display_name": "Pearl White",
        "paint_code": "CA_",
        "slug": "pearl-white-ca",
        "reference_url": "https://www.paintscratch.com/colors/amc/pearl-white-ca/",
        "source_label": "PaintScratch 1988 AMC",
        "hex_value": "#F9F7F7"
      },
      {
        "display_name": "Buff Yellow",
        "paint_code": "CB",
        "slug": "buff-yellow-cb",
        "reference_url": "https://www.paintscratch.com/colors/amc/buff-yellow-cb/",
        "source_label": "PaintScratch 1988 AMC",
        "hex_value": "#E6E4A4"
      },
      {
        "display_name": "Light Baltic Metallic",
        "paint_code": "CD",
        "slug": "light-baltic-metallic-cd",
        "reference_url": "https://www.paintscratch.com/colors/amc/light-baltic-metallic-cd/",
        "source_label": "PaintScratch 1988 AMC",
        "hex_value": "#B4C2C8"
      },
      {
        "display_name": "Bright White",
        "paint_code": "CR",
        "slug": "bright-white-cr",
        "reference_url": "https://www.paintscratch.com/colors/amc/bright-white-cr/",
        "source_label": "PaintScratch 1988 AMC",
        "hex_value": "#FFFFFF"
      },
      {
        "display_name": "Flash Red Pearl Metallic",
        "paint_code": "CV",
        "slug": "flash-red-pearl-metallic-cv",
        "reference_url": "https://www.paintscratch.com/colors/amc/flash-red-pearl-metallic-cv/",
        "source_label": "PaintScratch 1988 AMC",
        "hex_value": "#E21436"
      },
      {
        "display_name": "Coffee",
        "paint_code": "CW",
        "slug": "coffee-cw",
        "reference_url": "https://www.paintscratch.com/colors/amc/coffee-cw/",
        "source_label": "PaintScratch 1988 AMC",
        "hex_value": "#B79565"
      },
      {
        "display_name": "Charcoal Metallic",
        "paint_code": "CX",
        "slug": "charcoal-metallic-cx",
        "reference_url": "https://www.paintscratch.com/colors/amc/charcoal-metallic-cx/",
        "source_label": "PaintScratch 1988 AMC",
        "hex_value": "#737373"
      },
      {
        "display_name": "Signal Red",
        "paint_code": "CY",
        "slug": "signal-red-cy",
        "reference_url": "https://www.paintscratch.com/colors/amc/signal-red-cy/",
        "source_label": "PaintScratch 1988 AMC",
        "hex_value": "#ED1717"
      },
      {
        "display_name": "Medium Suede Metallic",
        "paint_code": "GK4/PK4",
        "slug": "medium-suede-metallic-gk4pk4",
        "reference_url": "https://www.paintscratch.com/colors/amc/medium-suede-metallic-gk4pk4/",
        "source_label": "PaintScratch 1988 AMC",
        "hex_value": "#8A765C"
      }
    ]
  }
}